{
 "absolute_value": 0,
 "align_labels_right": 0,
 "creation": "2024-06-10 13:14:15.354071",
 "css": "body {\n  padding: 0;\n  margin: 0;\n}\n\n.print-format td, .print-format th {\n    padding: 3px 10px !important;\n}\n\n.container-2 {\n  width: 100%;\n  margin: 0;\n  display: flex;\n  padding: 10px 0px;\n}\n\n.container-2 .first {\n  width: 100%;\n}\n.first .data label{\n  width: 200px;\n}\n\ntable,\nth {\n  border: 1px solid black;\n  border-collapse: collapse;\n}\n\n.color-pic{\n    width: 100%;\n    background-color: #3370a8;\n}\n\n.color-pic th:first-child{\n    width: 60%;\n}\n\n.head-table{\n    background-color: #deeaf6;\n}\n\n.f-tbl-td{\n    background-color: #d0cece;\n}\n\n\n#change-color {\n    background-color: #d5dce4 !important;\n}\n\n.f-td{\n    width: 120px !important;\n}\n\n.color-pic th{\n    font-weight: bold;\n    text-align: center;\n    color: #fff;\n}\n\nth,\ntd {\n  padding-left: 10px;\n  border: 1px solid black;\n  font-weight: 400;\n  color: #000;\n}\n\n#sec-tbl{\n    margin-top: 25px;\n}\n\n#sec-tbl th{\n    background-color: #bdd6ee;\n}\n\n.center {\n  text-align: center;\n}\n.left {\n    font-weight: bold;\n  text-align: end !important;\n  width: 20%;\n}\n\n.right{\n   width: auto;\n}\n\n.head {\n    display: flex;\n    align-items: center;\n    justify-content: space-between;\n    margin-bottom: 50px;\n    padding: 0 15px;\n}\n\n.head h3{\n    color: #000;\n    font-size: 30px;\n}\n\n.f-tr th{\n    color: #000;\n    font-weight: bold;\n    text-align: center\n}\n\n\ntfoot tr td{\n    font-weight: bold;\n}\n\ntfoot tr{\n    background-color: #ededed;\n}\n\ntfoot tr:first-child,\ntfoot tr:last-child{\n    background-color: #bdd6ee !important;\n}\n\n\n#term-cond{\n    margin: 50px 0;\n}\n\n.container .head{\n    margin: 0;\n}\n\n.container h4{\n    color: #000;\n    font-size: 20px;\n    font-weight: bold;\n}\n\n\nul{\n margin-left: 20px;   \n}\n\nul li{\n    margin: 5px;\n    font-weight: 500;\n}\n.image img{\n        width: 118px;\n}\n\n.img img{\n    width: 250px;\n    float: right;\n    margin-right: 58px;\n}\n\n#foot h4{\n    color: #000;\n    font-size: 25px;\n    font-weight: 400;\n}\n\n#foot p{\n    font-weight: 500;\n    font-size: 18px;\n}\n\n",
 "custom_format": 1,
 "default_print_language": "en",
 "disabled": 0,
 "doc_type": "Purchase Order",
 "docstatus": 0,
 "doctype": "Print Format",
 "font_size": 14,
 "html": "    <div class=\"container-2\">\n        <div class=\"first\" id=\"first\">\n            <table class=\"head-table\" style=\"width:100%\">\n                <tr class=\"color-pic\">\n                    <th >Supplier</th>\n                    <th colspan=\"2\">Document Refrences</th>\n                </tr>\n                <tr class=\"f-tbl-td\">\n                    <td rowspan=\"3\" id=\"change-color\">{{doc.supplier}}</td>\n                    <td class=\"left f-td\">Date:</td>\n                    <td>{{doc.transaction_date}}</td>\n                </tr>\n                {% if doc.contact_person %}\n                {% set contact = frappe.get_doc(\"Contact\", doc.contact_person) %}\n                <tr>\n                    <td class=\"left f-td\">PO NO:</td>\n                    <td>{{ contact.phone_nos[0].phone }}</td>\n                </tr>\n                {% endif %}\n                <tr class=\"f-tbl-td\">\n                    <td class=\"left f-td\">Quate Ref:</td>\n                    <td>{{doc.name}}</td>\n                </tr>\n            </table>\n        </div>\n    </div>\n    \n<div class=\"container-2\" id=\"sec-tbl\">\n    <div class=\"first\">\n         <table style=\"width:100%\">\n        <thead>\n            <tr class=\"f-tr\">\n                <th style=\"width: 40px;\">S.N</th>\n                <th class=\"center\">Description</th>\n                <th style=\"width: 100px;\">Qty.</th>\n                <th style=\"width: 130px;\">Unit Price</th>\n                <th style=\"width: 130px;\">Price</th>\n            </tr>\n            </thead>\n         <tbody>\n             {%- for item in doc.items -%}\n            <tr>\n                <td>{{item.idx}}</td>\n                <td>{{item.description}}</td>\n                <td class=\"center\">{{item.qty}}</td>\n                <td class=\"center\">{{item.rate}}</td>\n                <td class=\"center\">{{item.amount}}</td>\n            </tr>\n                {%- endfor -%}\n        </tbody>\n             <tfoot>\n                <tr>\n                    <td class=\"left right\" colspan=\"4\">Gross Amount: </td>\n                    <td>{{doc.grand_total}}</td>\n                </tr>\n                <tr>\n                    <td class=\"left right\" colspan=\"4\">Discount: </td>\n                    <td>{{doc.discount_amount}}</td>\n                </tr>\n                <tr>\n                    <td class=\"left right\" colspan=\"4\">Net Amount: </td>\n                    <td>{{doc.net_total}}</td>\n                </tr>\n            </tfoot>\n        </table>\n    </div>\n</div>\n    \n    \n<div class=\"container\" id=\"term-cond\">\n    <div class=\"head\">\n        <h4>Terms & Condition</h4>\n    </div>\n     <div>{{doc.terms}}</div>\n</div>\n    \n    \n<div class=\"container\" id=\"foot\">\n    <div class=\"img\">\n    <img src=\"/files/1print-image.webp\" alt=\"\">\n    </div>    \n    <div class=\"image\">\n    <img src=\"/files/2print-image.webp\" alt=\"\">\n    </div>    <p>Thanks & Regards</p>\n    <h5>Md. Hassan Baba</h5>\n</div>\n\n",
 "idx": 0,
 "line_breaks": 0,
 "margin_bottom": 15.0,
 "margin_left": 15.0,
 "margin_right": 15.0,
 "margin_top": 15.0,
 "modified": "2024-06-10 22:30:04.349571",
 "modified_by": "Administrator",
 "module": "Izzu",
 "name": "Purchase Order",
 "owner": "Administrator",
 "page_number": "Hide",
 "print_format_builder": 0,
 "print_format_builder_beta": 0,
 "print_format_type": "Jinja",
 "raw_printing": 0,
 "show_section_headings": 0,
 "standard": "Yes"
}